wmspro/__init__.py
wmspro/action.py
wmspro/const.py
wmspro/destination.py
wmspro/room.py
wmspro/scene.py
wmspro/webcontrol.py
pywmspro-0.3.3.dist-info/METADATA
pywmspro-0.3.3.dist-info/WHEEL
pywmspro-0.3.3.dist-info/licenses/LICENSE
pywmspro-0.3.3.dist-info/RECORD
