Metadata-Version: 2.4
Name: pywmspro
Version: 0.3.3
Summary: Python library for WMS WebControl pro API
Author-email: Marc Hoersken <info@marc-hoersken.de>
License-Expression: Apache-2.0
License-File: LICENSE
Keywords: warema,webcontrol,wms
Requires-Python: >=3.9
Requires-Dist: aiohttp>=3.11.18
